ismrmrdviewer/__init__.py
ismrmrdviewer/__main__.py
ismrmrdviewer/ui/FileWidget.py
ismrmrdviewer/ui/MainWindow.py
ismrmrdviewer/ui/__init__.py
ismrmrdviewer/viewer/AcquisitionViewer.py
ismrmrdviewer/viewer/HeaderViewer.py
ismrmrdviewer/viewer/ImageViewer.py
ismrmrdviewer/viewer/WaveformViewer.py
ismrmrdviewer/viewer/__init__.py
ismrmrdviewer/viewer/utils.py
ismrmrdviewer-0.2.1.dist-info/LICENSE.txt
ismrmrdviewer-0.2.1.dist-info/METADATA
ismrmrdviewer-0.2.1.dist-info/WHEEL
ismrmrdviewer-0.2.1.dist-info/entry_points.txt
ismrmrdviewer-0.2.1.dist-info/top_level.txt
ismrmrdviewer-0.2.1.dist-info/RECORD
